virtool_cli/__init__.py
virtool_cli/build.py
virtool_cli/divide.py
virtool_cli/hmm.py
virtool_cli/isolate.py
virtool_cli/ref.py
virtool_cli/repair.py
virtool_cli/run.py
virtool_cli/taxid.py
virtool_cli/utils.py
virtool_cli/vfam.py
virtool_cli/vfam_annotation.py
virtool_cli/vfam_collapse.py
virtool_cli/vfam_console.py
virtool_cli/vfam_curate.py
virtool_cli/vfam_filter.py
virtool_cli/vfam_markov.py
virtool_cli/vfam_msa.py
virtool_cli/vfam_polyprotein.py
virtool_cli-1.0.1.dist-info/METADATA
virtool_cli-1.0.1.dist-info/WHEEL
virtool_cli-1.0.1.dist-info/entry_points.txt
virtool_cli-1.0.1.dist-info/RECORD
