Metadata-Version: 2.1
Name: virtool-cli
Version: 1.0.1
Summary: CLI Tool for working with Virtool data
License: MIT
Author: Ian Boyes
Author-email: igboyes@gmail.com
Maintainer: Ian Boyes
Maintainer-email: igboyes@gmail.com
Requires-Python: >=3.7,<4.0
Classifier: License :: OSI Approved :: MIT License
Classifier: Programming Language :: Python :: 3
Classifier: Programming Language :: Python :: 3.7
Classifier: Programming Language :: Python :: 3.8
Classifier: Programming Language :: Python :: 3.9
Classifier: Programming Language :: Python :: 3.10
Classifier: Programming Language :: Python :: 3.11
Requires-Dist: aiofiles (>0.5.0)
Requires-Dist: aiohttp (==3.6.2)
Requires-Dist: aiojobs (==0.2.2)
Requires-Dist: arrow (==0.16.0)
Requires-Dist: biopython (>=1.79,<2.0)
Requires-Dist: click (>=8.0.3,<9.0.0)
Requires-Dist: pytest-asyncio (>=0.16.0,<0.17.0)
Requires-Dist: pytest-mock (>=3.6.1,<4.0.0)
Requires-Dist: rich (>=7.0.0,<8.0.0)
